[{"text":"In your eyes there's a heavy blue","time":"0","time1":"4000"},
{"text":"One to love and one to lose","time":"4000","time1":"7000"},
{"text":"Sweet divine, the heavy truth","time":"7000","time1":"10200"},
{"text":"Water or wine, don't make me choose","time":"10200","time1":"13200"},
{"text":"I wanna feel the way that we did that summer night, night","time":"13200","time1":"19500"},
{"text":"Drunk on a feeling, alone with the stars in the sky","time":"19500","time1":"25500"},
{"text":"I've been running through the jungle","time":"25500","time1":"27700"},
{"text":"I've been running with the wolves","time":"27700","time1":"29200"},
{"text":"To get to you, to get to you","time":"29200","time1":"32500"},
{"text":"I've been down the darkest alleys","time":"32500","time1":"34200"},
{"text":"Saw the dark side of the moon","time":"34200","time1":"36000"},
{"text":"To get to you, to get to you","time":"36000","time1":"39200"},
{"text":"I've looked for love in every stranger","time":"39200","time1":"40800"},
{"text":"Took too much to ease the anger","time":"40800","time1":"42400"},
{"text":"All for you, yeah, all for you","time":"42400","time1":"45700"},
{"text":"I've been running through the jungle","time":"45700","time1":"47200"},
{"text":"I've been crying with the wolves","time":"47200","time1":"49000"},
{"text":"To get to you, to get to you, (Oh, to get to you)","time":"49000","time1":"53000"},
{"text":"#","written_by":"Alexandra Leah Tamposi, Andrew Watt, Brian Lee, Carl Rosen, Louis Bell, Marshmello, Selena Gomez\n\n\n\n\n\n\n\n\n\n\n\n\n\n\n\n\n\n\n\n\n\n\n\n"}]
